si4pipeline_gui/__init__.py
si4pipeline_gui/app.py
si4pipeline_gui/cli.py
si4pipeline_gui/schemas.barfi
si4pipeline_gui/blocks/__init__.py
si4pipeline_gui/blocks/algorithm_blocks.py
si4pipeline_gui/blocks/base_test.py
si4pipeline_gui/blocks/load_blocks.py
si4pipeline_gui/blocks/node_factory.py
si4pipeline_gui/blocks/test_blocks.py
si4pipeline_gui/dataset/abalone.pkl
si4pipeline_gui/dataset/concrete.pkl
si4pipeline_gui/dataset/prostate_cancer.pkl
si4pipeline_gui/dataset/red_wine.pkl
si4pipeline_gui-0.7.0.dist-info/licenses/LICENSE.md
si4pipeline_gui-0.7.0.dist-info/METADATA
si4pipeline_gui-0.7.0.dist-info/WHEEL
si4pipeline_gui-0.7.0.dist-info/entry_points.txt
si4pipeline_gui-0.7.0.dist-info/top_level.txt
si4pipeline_gui-0.7.0.dist-info/RECORD
