Metadata-Version: 2.4
Name: si4pipeline-gui
Version: 0.7.0
Summary: A Streamlit-based GUI for statistical test for feature selection pipeline via selective inference
Author: Takeuchi Lab
Maintainer-email: Shuichi NISHINO <nishino.shuichi.nagoyaml@gmail.com>
License-Expression: MIT
Project-URL: repository, https://github.com/Takeuchi-Lab-SI-Group/si4pipeline-gui
Classifier: Programming Language :: Python :: 3.10
Classifier: Programming Language :: Python :: 3.11
Classifier: Programming Language :: Python :: 3.12
Classifier: Programming Language :: Python :: 3.13
License-File: LICENSE.md
Requires-Dist: si4pipeline==1.0.1
Requires-Dist: streamlit>=1.45.0
Requires-Dist: barfi==1.1.0
Dynamic: license-file
